vecflowapi/Client.py
vecflowapi/Pipeline.py
vecflowapi/__init__.py
vecflowapi/api_errors.py
vecflowApi-0.3.6.dist-info/METADATA
vecflowApi-0.3.6.dist-info/WHEEL
vecflowApi-0.3.6.dist-info/top_level.txt
vecflowApi-0.3.6.dist-info/RECORD
