Metadata-Version: 2.1
Name: vecflowApi
Version: 0.3.6
Summary: API wrapper for the VecFlow API
Home-page: https://github.com/VecFlow/VecFlow
Author: VecFlow Team
Classifier: Programming Language :: Python :: 3
Classifier: License :: OSI Approved :: MIT License
Classifier: Operating System :: OS Independent
Requires-Dist: requests
Requires-Dist: werkzeug
